mips_processor/verilog_code/mux.v
module mux_two(first,second,flag,signal);
input [31:0] first;
input [31:0] second;
input flag;
output reg [31:0] signal;

always@(*)
begin
    if(flag == 1)
        signal <= first;
    else
        signal <= second;
    //$display("mux flag: %d", flag);
end
endmodule

mips_processor/verilog_code/alu.v
module alu(lvalue, rvalue, aluOP, result);
input [31:0] lvalue;
input [31:0] rvalue;
input [3:0] aluOP;
output reg [31:0] result;
reg [31:0] truevall;
reg [31:0] truevalr;
always @(lvalue, rvalue)
begin
    if(lvalue == `dc32)
        truevall = 0;
    else
        truevall = lvalue;
    if(rvalue == `dc32)
        truevalr = 0;
    else
        truevalr = rvalue;
    case(aluOP)
        `ALU_add: result = truevall+truevalr;//lvalue + rvalue;
        `ALU_OR: result = truevall|truevalr;//lvalue | rvalue;
    endcase
end
endmodule

mips_processor/verilog_code/sign_extend.v
module sign_extend(inst, extend);
input [15:0] inst;
output reg [31:0] extend;
reg one;
reg zero;
initial
begin
    one = 1;
    zero = 0;
end
always @(*)
begin
    if(inst[15] == 0)
        extend = {{16{zero}}, inst};
    else
        extend = {{16{one}}, inst};
end
endmodule

mips_processor/verilog_code/reg_mem.v
module reg_mem(rreg1, rreg2, wreg, wdata, reg_write, clk, rdata1, rdata2, rv0, ra0);
input [4:0] rreg1;
input [4:0] rreg2;
input [4:0] wreg;
input [31:0] wdata;
input reg_write;
input clk;
output reg [31:0] rdata1;
output reg [31:0] rdata2;
//hacky way to do system calls
output reg [31:0] rv0;
output reg [31:0] ra0;
//register memory
reg [31:0] regs [31:0];
initial
begin
regs[`r0] = 0;
end

always @(negedge clk)
begin
    //$display("regs 0 is %x, rreg %b, rdata %x, reg at rreg %x", regs[0], rreg1, rdata1, regs[rreg1]);
    rdata1 = regs[rreg1];
    rdata2 = regs[rreg2];
    rv0 = regs[`v0];
    ra0 = regs[`a0];
    //$display("rdata1 %d from reg %b", rdata1, rreg1);
end

always @(posedge clk)
begin
    if(reg_write)
    begin
        regs[wreg] = wdata;
        //$display("%b register has %d data, the value should be %d", wreg, regs[wreg], regs[rreg1]); 
    end
    rv0 = regs[`v0];
    ra0 = regs[`a0];
end
endmodule

mips_processor/verilog_code/mini_mux.v
module mini_mux(first,second,flag,signal);
input [4:0] first;
input [4:0] second;
input flag;
output reg [4:0] signal;

always@(*)
begin
    if(flag == 1)
        signal = first;
    else
        signal = second;
    //$display("Wreg is %d", signal);
end
endmodule

mips_processor/verilog_code/control.v
//will add more to this module as neccessary
module control(instruction, jump, reg_dst, branch, mem_read, mem_to_reg, alu_op, reg_write, alu_src, mem_write);
input [31:0] instruction;
output reg jump;
output reg reg_dst;
output reg branch;
output reg mem_read;
output reg mem_to_reg;
output reg [3:0] alu_op;
output reg reg_write;
output reg alu_src;
output reg mem_write;


reg zero;
reg one;


//Uses a large case statement to assign flags. There may be a more efficient way to do this, and will be updated if neccessary
always @(instruction)
begin
    case(instruction[`op])
    `ADDI:
    begin
        reg_dst = zero;
        jump = zero;
        branch = zero;
        mem_read = zero;
        mem_to_reg = zero;
        alu_op = `ALU_add;
        reg_write = one;
        alu_src = one;
        mem_write = zero;
    end
    `ADDIU:
    begin
        reg_dst = zero;
        jump = zero;
        branch = zero;
        mem_read = zero;
        mem_to_reg = zero;
        alu_op = `ALU_add;
        reg_write = one;
        alu_src = one;
        mem_write = zero;
    end

    `ORI:
    begin
        reg_dst = zero;
        jump = zero;
        branch = zero;
        mem_read = zero;
        mem_to_reg = zero;
        alu_op = `ALU_OR;
        reg_write = one;
        alu_src = one;
        mem_write = zero; 
    end
    `LW:
    begin
        reg_dst = zero;
        jump = zero;
        branch = zero;
        mem_read = one;
        mem_to_reg = one;
        alu_op = `ALU_add;
        reg_write = one;
        alu_src = one;
        mem_write = zero;  
    end
    `SW:
    begin
        reg_dst = zero;
        jump = zero;
        branch = zero;
        mem_read = zero;
        mem_to_reg = zero;
        alu_op = `ALU_add;
        reg_write = zero;
        alu_src = one;
        mem_write = one;
    end
    `BEQ:
    begin
        reg_dst = zero;
        jump = zero;
        branch = one;
        mem_read = zero;
        mem_to_reg = zero;
        alu_op = `ALU_sub;
        reg_write = zero;
        alu_src = zero;
        mem_write = zero; 
    end
    `BNE:
    begin
        reg_dst = zero;
        jump = zero;
        branch = one;
        mem_read = zero;
        mem_to_reg = zero;
        alu_op = `ALU_sub;
        reg_write = zero;
        alu_src = zero;
        mem_write = zero; 
    end
    `J:
    begin
        reg_dst = zero;
        jump = one;
        branch = zero;
        mem_read = zero;
        mem_to_reg = zero;
        alu_op = zero;
        reg_write = zero;
        alu_src = zero;
        mem_write = zero;
    end
    `SPECIAL:
    begin
        reg_dst = one;
        jump = zero;
        branch = one;
        mem_read = zero;
        mem_to_reg = zero;
        reg_write = one;
        alu_src = zero;
        mem_write = zero;
        case(instruction[`function])
        `ADD: alu_op = `ALU_add;
        `SUB: alu_op = `ALU_sub;
        `AND: alu_op = `ALU_AND;
        `OR: alu_op = `ALU_OR;
        `SLT: alu_op = `ALU_slt;
        default: 
        begin
            alu_op = zero;
            reg_write = zero;
            branch = zero;
        end
        endcase
    end
    default:
    begin
        reg_dst = zero;
        jump = zero;
        branch = zero;
        mem_read = zero;
        mem_to_reg = zero;
        alu_op = zero;
        reg_write = zero;
        alu_src = zero;
        mem_write = zero;
    end
endcase
end
initial
begin
    zero = 0;
    one = 1;
end
endmodule

mips_processor/verilog_code/system.v
//A module for handeling syscalls
//Lucas Nicolois Sep 9, 2017

module system(inst, rv0, a0);
input [31:0] inst;
input [31:0] rv0;
input [31:0] a0;

always@(inst)
begin
    if(inst == 8'h0c)
    begin
        case(rv0)
            1: $display("%d", a0);
            10: $finish;
        endcase
    end
end
endmodule

mips_processor/verilog_code/mem.v
module memory(readAddress, memInstruction);
input [31:0] readAddress; 
output reg [31:0] memInstruction;

reg [31:0] mem [32'h100000:32'h101000];
initial begin
  $readmemh("mips_code/add_test.v"
  /*"jump.in"*/, mem);
end
reg [31:0] wordAddress;
always @(readAddress)
begin
  wordAddress = readAddress >> 2;
  memInstruction = mem[wordAddress];
  //$display("readAddress: %x", readAddress);
end
endmodule

mips_processor/verilog_code/shifter.v
module shifter_two(ins_value, pc_four, out);
input [31:0] ins_value;
input [31:0] pc_four;
output reg [31:0] out;
always @(*)
begin
    out = pc_four[31:28] + (ins_value[25:0] << 2);
    //$display("shift %x, cur ins_value %x", out, ins_value);
end
    endmodule

mips_processor/verilog_code/add.v
module adder(left, right, result);
input [31:0] left;
input [31:0] right;
output [31:0] result;
assign result = left + right;

endmodule

mips_processor/verilog_code/pc.v
module program_counter(clock, next_count, cur_count);
input [31:0] next_count;
input clock;
output reg [31:0] cur_count;

always @(posedge clock)
begin
    cur_count <= next_count;
    //$display("Current address: %x", cur_count);
end
initial
begin
    cur_count = 32'h00400000;
end

endmodule

mips_processor/verilog_code/test_bench.v
`include "mips.h"
module test;
reg clk;

//pc variables
wire [31:0] nxtc;
wire [31:0] curc;
wire [31:0] p4;
reg [31:0] up;
wire [31:0] inst;
wire [31:0] jadd;

//system variables
wire [31:0] rv0;
wire [31:0] ra0;

//control variables
wire jump;
wire reg_dst;
wire branch;
wire mem_read;
wire mem_to_reg;
wire [3:0] alu_op;
wire reg_write;
wire alu_src;
wire mem_write;

//register memory variables
wire [4:0] wreg;
wire [31:0] wdata;
wire [31:0] rdata1;
wire [31:0] rdata2;

//alu variables
wire [31:0] idata;
wire [31:0] alu_result;
wire [31:0] rvalue;

//address variables
wire [31:0] mem_data;

//pc decleration
program_counter pc(clk, nxtc, curc);
adder ad1(curc, up, p4);
shifter_two shif2(inst, p4, jadd);
mux_two mux1(jadd, p4, jump, nxtc);

//instruction memory dec
memory mem(nxtc, inst);

//system decleration
system sys(inst, rv0, ra0);

//control decleration
control cntrl(inst, jump, reg_dst, branch, mem_read, mem_to_reg, alu_op, reg_write, alu_src, mem_write);

//register memory decleration
mini_mux mini(inst[`rd], inst[`rt], reg_dst, wreg);
reg_mem regs(inst[`rs], inst[`rt], wreg, wdata, reg_write, clk, rdata1, rdata2, rv0, ra0);

//alu decleration
mux_two mux_alu(idata, rdata2, alu_src, rvalue);
sign_extend sign_ex(inst[`immediate], idata);
alu alu1(rdata1, rvalue, alu_op, alu_result);

//address decleration
//to do
mux_two write_mux(mem_data, alu_result, mem_to_reg, wdata);

//clock
always
begin
    #10 clk = ~clk;
   /*if(inst == 0)
        $finish;
*/
end

//test code here
initial
begin
    $dumpfile("test.vcd");
    $dumpvars(0,test);
    clk = 0;
    up = 4;
    $monitor("curent address is %h, the current instruction is %h", curc, inst);
end
endmodule

mips_processor/test.vcd
$date
	Fri Sep 15 15:03:46 2017
$end
$version
	Icarus Verilog
$end
$timescale
	1s
$end
$scope module test $end
$var wire 32 ! mem_data [31:0] $end
$var wire 5 " wreg [4:0] $end
$var wire 32 # wdata [31:0] $end
$var wire 32 $ rvalue [31:0] $end
$var wire 32 % rv0 [31:0] $end
$var wire 1 & reg_write $end
$var wire 1 ' reg_dst $end
$var wire 32 ( rdata2 [31:0] $end
$var wire 32 ) rdata1 [31:0] $end
$var wire 32 * ra0 [31:0] $end
$var wire 32 + p4 [31:0] $end
$var wire 32 , nxtc [31:0] $end
$var wire 1 - mem_write $end
$var wire 1 . mem_to_reg $end
$var wire 1 / mem_read $end
$var wire 1 0 jump $end
$var wire 32 1 jadd [31:0] $end
$var wire 32 2 inst [31:0] $end
$var wire 32 3 idata [31:0] $end
$var wire 32 4 curc [31:0] $end
$var wire 1 5 branch $end
$var wire 1 6 alu_src $end
$var wire 32 7 alu_result [31:0] $end
$var wire 4 8 alu_op [3:0] $end
$var reg 1 9 clk $end
$var reg 32 : up [31:0] $end
$scope module ad1 $end
$var wire 32 ; right [31:0] $end
$var wire 32 < result [31:0] $end
$var wire 32 = left [31:0] $end
$upscope $end
$scope module alu1 $end
$var wire 32 > rvalue [31:0] $end
$var wire 32 ? lvalue [31:0] $end
$var wire 4 @ aluOP [3:0] $end
$var reg 32 A result [31:0] $end
$var reg 32 B truevall [31:0] $end
$var reg 32 C truevalr [31:0] $end
$upscope $end
$scope module cntrl $end
$var wire 32 D instruction [31:0] $end
$var reg 4 E alu_op [3:0] $end
$var reg 1 6 alu_src $end
$var reg 1 5 branch $end
$var reg 1 0 jump $end
$var reg 1 / mem_read $end
$var reg 1 . mem_to_reg $end
$var reg 1 - mem_write $end
$var reg 1 F one $end
$var reg 1 ' reg_dst $end
$var reg 1 & reg_write $end
$var reg 1 G zero $end
$upscope $end
$scope module mem $end
$var wire 32 H readAddress [31:0] $end
$var reg 32 I memInstruction [31:0] $end
$var reg 32 J wordAddress [31:0] $end
$upscope $end
$scope module mini $end
$var wire 5 K first [4:0] $end
$var wire 1 ' flag $end
$var wire 5 L second [4:0] $end
$var reg 5 M signal [4:0] $end
$upscope $end
$scope module mux1 $end
$var wire 1 0 flag $end
$var wire 32 N second [31:0] $end
$var wire 32 O first [31:0] $end
$var reg 32 P signal [31:0] $end
$upscope $end
$scope module mux_alu $end
$var wire 1 6 flag $end
$var wire 32 Q second [31:0] $end
$var wire 32 R first [31:0] $end
$var reg 32 S signal [31:0] $end
$upscope $end
$scope module pc $end
$var wire 1 9 clock $end
$var wire 32 T next_count [31:0] $end
$var reg 32 U cur_count [31:0] $end
$upscope $end
$scope module regs $end
$var wire 1 9 clk $end
$var wire 1 & reg_write $end
$var wire 5 V rreg1 [4:0] $end
$var wire 5 W rreg2 [4:0] $end
$var wire 5 X wreg [4:0] $end
$var wire 32 Y wdata [31:0] $end
$var reg 32 Z ra0 [31:0] $end
$var reg 32 [ rdata1 [31:0] $end
$var reg 32 \ rdata2 [31:0] $end
$var reg 32 ] rv0 [31:0] $end
$upscope $end
$scope module shif2 $end
$var wire 32 ^ ins_value [31:0] $end
$var wire 32 _ pc_four [31:0] $end
$var reg 32 ` out [31:0] $end
$upscope $end
$scope module sign_ex $end
$var wire 16 a inst [15:0] $end
$var reg 32 b extend [31:0] $end
$var reg 1 c one $end
$var reg 1 d zero $end
$upscope $end
$scope module sys $end
$var wire 32 e a0 [31:0] $end
$var wire 32 f inst [31:0] $end
$var wire 32 g rv0 [31:0] $end
$upscope $end
$scope module write_mux $end
$var wire 32 h first [31:0] $end
$var wire 1 . flag $end
$var wire 32 i second [31:0] $end
$var reg 32 j signal [31:0] $end
$upscope $end
$upscope $end
$enddefinitions $end
#0
$dumpvars
bx j
bx i
bz h
bx g
b0 f
bx e
0d
1c
b0 b
b0 a
b0 `
b10000000000000000000100 _
b0 ^
bx ]
bx \
bx [
bx Z
bx Y
b0 X
b0 W
b0 V
b10000000000000000000000 U
b10000000000000000000100 T
bx S
b0 R
bx Q
b10000000000000000000100 P
b0 O
b10000000000000000000100 N
b0 M
b0 L
b0 K
b100000000000000000001 J
b0 I
b10000000000000000000100 H
0G
1F
b0 E
b0 D
bx C
bx B
bx A
b0 @
bx ?
bx >
b10000000000000000000000 =
b10000000000000000000100 <
b100 ;
b100 :
09
b0 8
bx 7
06
05
b10000000000000000000000 4
b0 3
b0 2
b0 1
00
0/
0.
0-
b10000000000000000000100 ,
b10000000000000000000100 +
bx *
bx )
bx (
1'
0&
bx %
bx $
bx #
b0 "
bz !
$end
#10
b100000000000000000010 J
b10000000000000000001000 ,
b10000000000000000001000 H
b10000000000000000001000 P
b10000000000000000001000 T
b10000000000000000001000 +
b10000000000000000001000 <
b10000000000000000001000 N
b10000000000000000001000 _
b10000000000000000000100 4
b10000000000000000000100 =
b10000000000000000000100 U
19
#20
b0 C
b0 $
b0 >
b0 S
b0 B
b0 (
b0 Q
b0 \
b0 )
b0 ?
b0 [
09
#30
b100000000000000000011 J
b10000000000000000001100 ,
b10000000000000000001100 H
b10000000000000000001100 P
b10000000000000000001100 T
b10000000000000000001100 +
b10000000000000000001100 <
b10000000000000000001100 N
b10000000000000000001100 _
b10000000000000000001000 4
b10000000000000000001000 =
b10000000000000000001000 U
19
#40
09
#50
b100000000000000000100 J
b10000000000000000010000 ,
b10000000000000000010000 H
b10000000000000000010000 P
b10000000000000000010000 T
b10000000000000000010000 +
b10000000000000000010000 <
b10000000000000000010000 N
b10000000000000000010000 _
b10000000000000000001100 4
b10000000000000000001100 =
b10000000000000000001100 U
19
#60
09
#70
b100000000000000000101 J
b10000000000000000010100 ,
b10000000000000000010100 H
b10000000000000000010100 P
b10000000000000000010100 T
b10000000000000000010100 +
b10000000000000000010100 <
b10000000000000000010100 N
b10000000000000000010100 _
b10000000000000000010000 4
b10000000000000000010000 =
b10000000000000000010000 U
19
#80
09
#90
b1111111111111111xxxxxxxxxxxxxxxx 3
b1111111111111111xxxxxxxxxxxxxxxx R
b1111111111111111xxxxxxxxxxxxxxxx b
bx "
bx M
bx X
bx a
bx W
bx V
bx L
bx K
0'
bx 1
bx O
bx `
bx 2
bx D
bx I
bx ^
bx f
b100000000000000000110 J
b10000000000000000011000 ,
b10000000000000000011000 H
b10000000000000000011000 P
b10000000000000000011000 T
b10000000000000000011000 +
b10000000000000000011000 <
b10000000000000000011000 N
b10000000000000000011000 _
b10000000000000000010100 4
b10000000000000000010100 =
b10000000000000000010100 U
19
#100
bx C
bx $
bx >
bx S
bx B
bx (
bx Q
bx \
bx )
bx ?
bx [
09
#110
b100000000000000000111 J
b10000000000000000011100 ,
b10000000000000000011100 H
b10000000000000000011100 P
b10000000000000000011100 T
b10000000000000000011100 +
b10000000000000000011100 <
b10000000000000000011100 N
b10000000000000000011100 _
b10000000000000000011000 4
b10000000000000000011000 =
b10000000000000000011000 U
19
#120
09
#130
b1 C
b1 $
b1 >
b1 S
b1 3
b1 R
b1 b
b1000 "
b1000 M
b1000 X
b1 a
b1000 W
b0 V
b1000 L
b0 K
16
1&
b10 8
b10 @
b10 E
b1000000000000000000100 1
b1000000000000000000100 O
b1000000000000000000100 `
b100100000010000000000000000001 2
b100100000010000000000000000001 D
b100100000010000000000000000001 I
b100100000010000000000000000001 ^
b100100000010000000000000000001 f
b100000000000000001000 J
b10000000000000000100000 ,
b10000000000000000100000 H
b10000000000000000100000 P
b10000000000000000100000 T
b10000000000000000100000 +
b10000000000000000100000 <
b10000000000000000100000 N
b10000000000000000100000 _
b10000000000000000011100 4
b10000000000000000011100 =
b10000000000000000011100 U
19
#140
b1 #
b1 Y
b1 j
b1 7
b1 A
b1 i
b0 B
b0 )
b0 ?
b0 [
09
#150
b10 #
b10 Y
b10 j
b10 7
b10 A
b10 i
b10 C
b10 $
b10 >
b10 S
b10 3
b10 R
b10 b
b1001 "
b1001 M
b1001 X
b10 a
b1001 W
b1001 L
b1001000000000000001000 1
b1001000000000000001000 O
b1001000000000000001000 `
b100100000010010000000000000010 2
b100100000010010000000000000010 D
b100100000010010000000000000010 I
b100100000010010000000000000010 ^
b100100000010010000000000000010 f
b100000000000000001001 J
b10000000000000000100100 ,
b10000000000000000100100 H
b10000000000000000100100 P
b10000000000000000100100 T
b10000000000000000100100 +
b10000000000000000100100 <
b10000000000000000100100 N
b10000000000000000100100 _
b10000000000000000100000 4
b10000000000000000100000 =
b10000000000000000100000 U
19
#160
09
#170
b1 #
b1 Y
b1 j
b1 7
b1 A
b1 i
b1 C
b1 $
b1 >
b1 S
b1 3
b1 R
b1 b
b10 "
b10 M
b10 X
b1 a
b10 W
b10 L
b10000000000000000100 1
b10000000000000000100 O
b10000000000000000100 `
b100100000000100000000000000001 2
b100100000000100000000000000001 D
b100100000000100000000000000001 I
b100100000000100000000000000001 ^
b100100000000100000000000000001 f
b100000000000000001010 J
b10000000000000000101000 ,
b10000000000000000101000 H
b10000000000000000101000 P
b10000000000000000101000 T
b10000000000000000101000 +
b10000000000000000101000 <
b10000000000000000101000 N
b10000000000000000101000 _
b10000000000000000100100 4
b10000000000000000100100 =
b10000000000000000100100 U
19
#180
09
#190
bx #
bx Y
bx j
bx 7
bx A
bx i
bx C
bx $
bx >
bx S
b10000000100000 3
b10000000100000 R
b10000000100000 b
b100 "
b100 M
b100 X
b10000000100000 a
b1000 W
b1001 V
b1000 L
b100 K
06
15
1'
b100101000001000000010000000 1
b100101000001000000010000000 O
b100101000001000000010000000 `
b1001010000010000000100000 2
b1001010000010000000100000 D
b1001010000010000000100000 I
b1001010000010000000100000 ^
b1001010000010000000100000 f
b100000000000000001011 J
b10000000000000000101100 ,
b10000000000000000101100 H
b10000000000000000101100 P
b10000000000000000101100 T
b10000000000000000101100 +
b10000000000000000101100 <
b10000000000000000101100 N
b10000000000000000101100 _
b10000000000000000101000 4
b10000000000000000101000 =
b10000000000000000101000 U
b1 %
b1 ]
b1 g
19
#200
b11 #
b11 Y
b11 j
b11 7
b11 A
b11 i
b1 C
b1 $
b1 >
b1 S
b10 B
b1 (
b1 Q
b1 \
b10 )
b10 ?
b10 [
09
#210
b1100 3
b1100 R
b1100 b
b0 "
b0 M
b0 X
b1100 a
b0 W
b0 V
b0 L
b0 K
05
0&
b0 8
b0 @
b0 E
b110000 1
b110000 O
b110000 `
b1100 2
b1100 D
b1100 I
b1100 ^
b1100 f
b100000000000000001100 J
b10000000000000000110000 ,
b10000000000000000110000 H
b10000000000000000110000 P
b10000000000000000110000 T
b10000000000000000110000 +
b10000000000000000110000 <
b10000000000000000110000 N
b10000000000000000110000 _
b10000000000000000101100 4
b10000000000000000101100 =
b10000000000000000101100 U
b11 *
b11 Z
b11 e
19
#220
b0 C
b0 $
b0 >
b0 S
b0 B
b0 (
b0 Q
b0 \
b0 )
b0 ?
b0 [
09
#230
b1010 #
b1010 Y
b1010 j
b1010 7
b1010 A
b1010 i
b1010 C
b1010 $
b1010 >
b1010 S
b1010 3
b1010 R
b1010 b
b10 "
b10 M
b10 X
b1010 a
b10 W
b10 L
16
1&
b10 8
b10 @
b10 E
0'
b10000000000000101000 1
b10000000000000101000 O
b10000000000000101000 `
b100100000000100000000000001010 2
b100100000000100000000000001010 D
b100100000000100000000000001010 I
b100100000000100000000000001010 ^
b100100000000100000000000001010 f
b100000000000000001101 J
b10000000000000000110100 ,
b10000000000000000110100 H
b10000000000000000110100 P
b10000000000000000110100 T
b10000000000000000110100 +
b10000000000000000110100 <
b10000000000000000110100 N
b10000000000000000110100 _
b10000000000000000110000 4
b10000000000000000110000 =
b10000000000000000110000 U
19
#240
b1 (
b1 Q
b1 \
09
#250
b1 C
b1 $
b1 >
b1 S
b1100 3
b1100 R
b1100 b
b0 "
b0 M
b0 X
b1100 a
b0 W
b0 L
0&
b0 8
b0 @
b0 E
06
05
1'
b110000 1
b110000 O
b110000 `
b1100 2
b1100 D
b1100 I
b1100 ^
b1100 f
b100000000000000001110 J
b10000000000000000111000 ,
b10000000000000000111000 H
b10000000000000000111000 P
b10000000000000000111000 T
b10000000000000000111000 +
b10000000000000000111000 <
b10000000000000000111000 N
b10000000000000000111000 _
b10000000000000000110100 4
b10000000000000000110100 =
b10000000000000000110100 U
b1010 %
b1010 ]
b1010 g
19
